2-verilog/adder/half_adder.v
`timescale 1ns/1ps
module half_adder(output Sum, Cout, input wire A, B);
    xor U1 (Sum, A, B);
    and U2 (Cout, A, B);
endmodule

/*
a b | s c
0 0 | 0 0
0 1 | 1 0
1 0 | 1 0
1 1 | 0 1
*/

2-verilog/adder/full_adder.v
`timescale 1ns/1ps
module full_adder(output wire Sum, Cout, input wire A, B, Cin);
    /* this whole things works without any delays on the second
    * call of half_adder (U2) since the half_adder itself uses gate-level
    * primitives which in themselves are just circuits. So here
    * you simply connect these two circuits with their wires and get a bigger
    * circuit which is again synthesizable since it is made from all
    * gate-level primitives.
    */
    wire HA1_Sum, HA1_Cout, HA2_Cout;
    half_adder U1 (.Sum(HA1_Sum), .Cout(HA1_Cout), .A(A), .B(B));
    half_adder U2 (.Sum(Sum), .Cout(HA2_Cout), .A(HA1_Sum), .B(Cin));

    // this needs to be delayed since everything is concurrent
    or U3 (Cout, HA1_Cout, HA2_Cout);
endmodule

/*
A B C | s c
0 0 0 | 0 0
0 0 1 | 1 0
0 1 0 | 1 0
0 1 1 | 0 1
1 0 0 | 1 0
1 0 1 | 0 1
1 1 0 | 0 1
1 1 1 | 1 1
*/

2-verilog/adder/full_adder_trace.vcd
$version Generated by VerilatedVcd $end
$date Mon Oct 12 20:26:12 2020
 $end
$timescale   1ps $end

 $scope module TOP $end
  $var wire  1 % A $end
  $var wire  1 & B $end
  $var wire  1 ' Cin $end
  $var wire  1 $ Cout $end
  $var wire  1 # Sum $end
  $scope module full_adder $end
   $var wire  1 % A $end
   $var wire  1 & B $end
   $var wire  1 ' Cin $end
   $var wire  1 $ Cout $end
   $var wire  1 ) HA1_Cout $end
   $var wire  1 ( HA1_Sum $end
   $var wire  1 * HA2_Cout $end
   $var wire  1 # Sum $end
   $scope module U1 $end
    $var wire  1 % A $end
    $var wire  1 & B $end
    $var wire  1 ) Cout $end
    $var wire  1 ( Sum $end
   $upscope $end
   $scope module U2 $end
    $var wire  1 ( A $end
    $var wire  1 ' B $end
    $var wire  1 * Cout $end
    $var wire  1 # Sum $end
   $upscope $end
  $upscope $end
 $upscope $end
$enddefinitions $end


#0
0#
0$
0%
0&
0'
0(
0)
0*
#1
1#
1%
1(
#2
0%
1&
#3
0#
1$
1%
0(
1)
#4
1#
0$
0%
0&
1'
0)
#5
0#
1$
1%
1(
1*
#6
0%
1&
#7
1#
1%
0(
1)
0*
