2-verilog/fsm-controller/fsm.v
/*
 * A simple FSM modelled as a Mealy machine i.e:
 *   next_state = f(current_state, inputs)
 *   (Moore: next_state = f(current_state), so current state already encodes
 *   inputs)
 *
 *
 */
module fsm
    (output reg out_open, out_close,
    input wire button, clk);

    parameter   closed = 1'b0,
                opened = 1'b1;

    // define fsm's memory
    reg current_state, next_state;

    always @ (posedge clk)
    begin: MEMORY
        current_state <= next_state;
    end

    // define how next_state gets updated based on inputs and current state;
    // this is combinational (no memory involved) so needs to trigger on all
    // inputs (current_state and button)
    // basically, define the mealy function
    // (combinational)
    always @ (current_state or button)
    begin: MEALY
        case (current_state)
            closed: if (button == 1'b1) next_state = opened; else next_state = closed;
            opened: if (button == 1'b1) next_state = closed; else next_state = opened;
            default: next_state = closed;
        endcase
    end

    // define how the outputs behave (combinational)
    always @ (current_state or button)
    begin: OUTPUT
        case (current_state)
            opened:
            if (button == 1'b1)
            begin
                out_open = 1'b1;
                out_close = 1'b0;
            end
            else
            begin
                out_open = 1'b0;
                out_close = 1'b0;
            end

            closed:
            if (button == 1'b1)
            begin
                out_open = 1'b0;
                out_close = 1'b1;
            end
            else
            begin
                out_open = 1'b0;
                out_close = 1'b0;
            end
            default:
            begin
                out_open = 1'b0;
                out_close = 1'b0;
            end
        endcase
    end
endmodule

2-verilog/fsm-controller/fsm_trace.vcd
$version Generated by VerilatedVcd $end
$date Mon Oct 19 13:15:34 2020
 $end
$timescale  10s $end

 $scope module TOP $end
  $var wire  1 % button $end
  $var wire  1 & clk $end
  $var wire  1 $ out_close $end
  $var wire  1 # out_open $end
  $scope module fsm $end
   $var wire  1 % button $end
   $var wire  1 & clk $end
   $var wire  1 ) closed [0:0] $end
   $var wire  1 ' current_state $end
   $var wire  1 ( next_state $end
   $var wire  1 * opened [0:0] $end
   $var wire  1 $ out_close $end
   $var wire  1 # out_open $end
  $upscope $end
 $upscope $end
$enddefinitions $end


#8
0#
1$
1%
0&
0'
1(
0)
1*
#10
1#
0$
1&
1'
0(
#15
0&
#18
0#
0%
1(
#20
1&
#25
0&
#28
#30
1&
#35
0&
#38
1#
1%
0(
#40
0#
1$
1&
0'
1(
#45
0&
#48
0$
0%
0(
#50
1&
#55
0&
#58
#60
1&
#65
0&
#68
1$
1%
1(
#70
1#
0$
1&
1'
0(
#75
0&
#78
0#
0%
1(
#80
1&
#85
0&
#88
#90
1&
#95
0&
#98
1#
1%
0(
#100
0#
1$
1&
0'
1(
#105
0&
#108
0$
0%
0(
#110
1&
#115
0&
#118
#120
1&
#125
0&
#128
1$
1%
1(
#130
1#
0$
1&
1'
0(
#135
0&
#138
0#
0%
1(
#140
1&
#145
0&
#148
#150
1&
#155
0&
#158
1#
1%
0(
#160
0#
1$
1&
0'
1(
#165
0&
#168
0$
0%
0(
#170
1&
#175
0&
#178
#180
1&
#185
0&
#188
1$
1%
1(
#190
1#
0$
1&
1'
0(
#195
0&
#198
0#
0%
1(
#200
1&
#205
0&
#208
#210
1&
#215
0&
#218
1#
1%
0(
#220
0#
1$
1&
0'
1(
#225
0&
#228
0$
0%
0(
#230
1&
#235
0&
#238
#240
1&
#245
0&
#248
1$
1%
1(
#250
1#
0$
1&
1'
0(
#255
0&
#258
0#
0%
1(
#260
1&
#265
0&
#268
#270
1&
#275
0&
#278
1#
1%
0(
#280
0#
1$
1&
0'
1(
#285
0&
#288
0$
0%
0(
#290
1&
#295
0&
#298
#300
1&
#305
0&
#308
1$
1%
1(
#310
1#
0$
1&
1'
0(
#315
0&
#318
0#
0%
1(
#320
1&
#325
0&
#328
#330
1&
#335
0&
#338
1#
1%
0(
#340
0#
1$
1&
0'
1(
#345
0&
#348
0$
0%
0(
#350
1&
#355
0&
#358
#360
1&
#365
0&
#368
1$
1%
1(
#370
1#
0$
1&
1'
0(
#375
0&
#378
0#
0%
1(
#380
1&
#385
0&
#388
#390
1&
#395
0&
#398
1#
1%
0(
#400
0#
1$
1&
0'
1(
#405
0&
#408
0$
0%
0(
#410
1&
#415
0&
#418
#420
1&
#425
0&
#428
1$
1%
1(
#430
1#
0$
1&
1'
0(
#435
0&
#438
0#
0%
1(
#440
1&
#445
0&
#448
#450
1&
#455
0&
#458
1#
1%
0(
#460
0#
1$
1&
0'
1(
#465
0&
#468
0$
0%
0(
#470
1&
#475
0&
#478
#480
1&
#485
0&
#488
1$
1%
1(
#490
1#
0$
1&
1'
0(
#495
0&
#498
0#
0%
1(
#500
1&
#505
0&
#508
#510
1&
#515
0&
#518
1#
1%
0(
#520
0#
1$
1&
0'
1(
#525
0&
#528
0$
0%
0(
#530
1&
#535
0&
#538
#540
1&
#545
0&
#548
1$
1%
1(
#550
1#
0$
1&
1'
0(
#555
0&
#558
0#
0%
1(
#560
1&
#565
0&
#568
#570
1&
#575
0&
#578
1#
1%
0(
#580
0#
1$
1&
0'
1(
#585
0&
#588
0$
0%
0(
#590
1&
#595
0&
#598
#600
1&
#605
0&
#608
1$
1%
1(
#610
1#
0$
1&
1'
0(
#615
0&
#618
0#
0%
1(
#620
1&
#625
0&
#628
#630
1&
#635
0&
#638
1#
1%
0(
#640
0#
1$
1&
0'
1(
#645
0&
#648
0$
0%
0(
#650
1&
#655
0&
#658
#660
1&
#665
0&
#668
1$
1%
1(
#670
1#
0$
1&
1'
0(
#675
0&
#678
0#
0%
1(
#680
1&
#685
0&
#688
#690
1&
#695
0&
#698
1#
1%
0(
#700
0#
1$
1&
0'
1(
#705
0&
#708
0$
0%
0(
#710
1&
#715
0&
#718
#720
1&
#725
0&
#728
1$
1%
1(
#730
1#
0$
1&
1'
0(
#735
0&
#738
0#
0%
1(
#740
1&
#745
0&
#748
#750
1&
#755
0&
#758
1#
1%
0(
#760
0#
1$
1&
0'
1(
#765
0&
#768
0$
0%
0(
#770
1&
#775
0&
#778
#780
1&
#785
0&
#788
1$
1%
1(
#790
1#
0$
1&
1'
0(
#795
0&
#798
0#
0%
1(
#800
1&
#805
0&
#808
#810
1&
#815
0&
#818
1#
1%
0(
#820
0#
1$
1&
0'
1(
#825
0&
#828
0$
0%
0(
#830
1&
#835
0&
#838
#840
1&
#845
0&
#848
1$
1%
1(
#850
1#
0$
1&
1'
0(
#855
0&
#858
0#
0%
1(
#860
1&
#865
0&
#868
#870
1&
#875
0&
#878
1#
1%
0(
#880
0#
1$
1&
0'
1(
#885
0&
#888
0$
0%
0(
#890
1&
#895
0&
#898
#900
1&
#905
0&
#908
1$
1%
1(
#910
1#
0$
1&
1'
0(
#915
0&
#918
0#
0%
1(
#920
1&
#925
0&
#928
#930
1&
#935
0&
#938
1#
1%
0(
#940
0#
1$
1&
0'
1(
#945
0&
#948
0$
0%
0(
#950
1&
#955
0&
#958
#960
1&
#965
0&
#968
1$
1%
1(
#970
1#
0$
1&
1'
0(
#975
0&
#978
0#
0%
1(
#980
1&
#985
0&
#988
#990
1&
#995
0&
#998
1#
1%
0(
#1000
0#
1$
1&
0'
1(
