2-verilog/serial-bit-sequence/serial.v
// given a bitstream from some transmiter, drive signal error if the sequence 111 is detected.
module serial
    (output reg error,
     input wire Din, clk, reset);

    // encode the states
    parameter   Start = 3'b000,
                D0_is_1 = 3'b001,
                D0_is_not_1 = 3'b010,
                D1_is_1 = 3'b011,
                D1_is_not_1 = 3'b100;

    // define memory
    reg [2:0] current_state, next_state;
    always @ (posedge clk or negedge reset)
    begin: MEMORY
        if (!reset) current_state <= Start;
        else        current_state <= next_state;
    end

    // define next_state based on inputs and current_state, so define the
    // mealy function
    always @ (current_state or Din)
    begin: NEXT_STATE_LOGIC
        case (current_state)
            Start:          if (Din == 1'b1) next_state = D0_is_1;  else next_state = D0_is_not_1;
            D0_is_1:        if (Din == 1'b1) next_state = D1_is_1;  else next_state = D1_is_not_1;
            D1_is_1:        next_state = Start;
            D0_is_not_1:    next_state = D1_is_not_1;
            D1_is_not_1:    next_state = Start;
            default:        next_state = Start;
        endcase
    end

    // define outputs based on current state and Din
    // output based on current_state and inputs, so previous results
    // not encoded in the current_state, so this is a mealy function
    always @ (current_state or Din)
    begin: OUTPUT_LOGIC
        case (current_state)
            D1_is_1: if (Din == 1'b1) error = 1'b1; else error = 1'b0; // mealy, since output not present in current state
            default: error = 1'b0;
        endcase
    end

endmodule

2-verilog/serial-bit-sequence/serial_trace.vcd
$version Generated by VerilatedVcd $end
$date Tue Oct 20 15:25:33 2020
 $end
$timescale   1ps $end

 $scope module TOP $end
  $var wire  1 $ Din $end
  $var wire  1 % clk $end
  $var wire  1 # error $end
  $var wire  1 & reset $end
  $scope module serial $end
   $var wire  3 * D0_is_1 [2:0] $end
   $var wire  3 + D0_is_not_1 [2:0] $end
   $var wire  3 , D1_is_1 [2:0] $end
   $var wire  3 - D1_is_not_1 [2:0] $end
   $var wire  1 $ Din $end
   $var wire  3 ) Start [2:0] $end
   $var wire  1 % clk $end
   $var wire  3 ' current_state [2:0] $end
   $var wire  1 # error $end
   $var wire  3 ( next_state [2:0] $end
   $var wire  1 & reset $end
  $upscope $end
 $upscope $end
$enddefinitions $end


#18
0#
1$
0%
1&
b000 '
b001 (
b000 )
b001 *
b010 +
b011 ,
b100 -
#20
1%
b001 '
b011 (
#25
0%
#28
0$
b100 (
#30
1%
b100 '
b000 (
#35
0%
#38
#40
1%
b000 '
b010 (
#45
0%
#48
1$
b001 (
#50
1%
b001 '
b011 (
#55
0%
#58
#60
1#
1%
b011 '
b000 (
#65
0%
#68
#70
0#
1%
b000 '
b001 (
#75
0%
#78
0$
b010 (
#80
1%
b010 '
b100 (
#85
0%
#88
#90
1%
b100 '
b000 (
#95
0%
#98
1$
#100
1%
b000 '
b001 (
#105
0%
#108
#110
1%
b001 '
b011 (
#115
0%
#118
0$
b100 (
#120
1%
b100 '
b000 (
#125
0%
#128
#130
1%
b000 '
b010 (
#135
0%
#138
1$
b001 (
#140
1%
b001 '
b011 (
#145
0%
#148
#150
1#
1%
b011 '
b000 (
#155
0%
#158
#160
0#
1%
b000 '
b001 (
#165
0%
#168
#170
1%
b001 '
b011 (
#175
0%
#178
#180
1#
1%
b011 '
b000 (
#185
0%
#188
#190
0#
1%
b000 '
b001 (
#195
0%
#198
#200
1%
b001 '
b011 (
#205
0%
#208
0$
b100 (
#210
1%
b100 '
b000 (
#215
0%
#218
#220
1%
b000 '
b010 (
